README.md
setup.py
sqlight/__init__.py
sqlight/connection.py
sqlight/dburl.py
sqlight/err.py
sqlight/row.py
sqlight.egg-info/PKG-INFO
sqlight.egg-info/SOURCES.txt
sqlight.egg-info/dependency_links.txt
sqlight.egg-info/top_level.txt
sqlight/platforms/__init__.py
sqlight/platforms/db.py
sqlight/platforms/factory.py
sqlight/platforms/keywords.py
sqlight/platforms/mysqlclient.py
sqlight/platforms/psycopg.py
sqlight/platforms/pymysql.py
sqlight/platforms/sqlite.py